certau/__init__.py
certau/lib/__init__.py
certau/lib/stix/__init__.py
certau/lib/stix/ais.py
certau/lib/stix/helpers.py
certau/lib/taxii/__init__.py
certau/lib/taxii/client.py
certau/lib/taxii/util.py
certau/scripts/__init__.py
certau/scripts/stixtransclient.py
certau/source/__init__.py
certau/source/base.py
certau/source/files.py
certau/source/taxii.py
certau/transform/__init__.py
certau/transform/base.py
certau/transform/brointel.py
certau/transform/csv.py
certau/transform/misp.py
certau/transform/snort.py
certau/transform/stats.py
certau/transform/text.py
cti_toolkit-1.1.0.dist-info/DESCRIPTION.rst
cti_toolkit-1.1.0.dist-info/METADATA
cti_toolkit-1.1.0.dist-info/RECORD
cti_toolkit-1.1.0.dist-info/WHEEL
cti_toolkit-1.1.0.dist-info/entry_points.txt
cti_toolkit-1.1.0.dist-info/metadata.json
cti_toolkit-1.1.0.dist-info/top_level.txt
